{
  "env": {
    "TERM": "xterm-256color",
    "SHELL": "/bin/bash"
  },
  "height": 31,
  "version": 1,
  "title": null,
  "width": 80,
  "duration": 73.36395,
  "command": null,
  "stdout": [
    [
      0.036794,
      "\u001b]0;root@vubuntu4dev: /home/vladves/vcs/repo_01\u0007root@vubuntu4dev:/home/vladves/vcs/repo_01# "
    ],
    [
      0.992643,
      "H"
    ],
    [
      0.586274,
      "i"
    ],
    [
      0.426154,
      "!"
    ],
    [
      0.414864,
      " "
    ],
    [
      0.325173,
      ")"
    ],
    [
      0.973419,
      "\b\u001b[K"
    ],
    [
      0.18147,
      "\b\u001b[K"
    ],
    [
      0.159049,
      "\b\u001b[K"
    ],
    [
      0.154,
      "\b\u001b[K"
    ],
    [
      0.169872,
      "\b\u001b[K"
    ],
    [
      0.144128,
      "\u0007"
    ],
    [
      0.535076,
      "n"
    ],
    [
      0.261858,
      "p"
    ],
    [
      0.324015,
      "m"
    ],
    [
      0.635175,
      " "
    ],
    [
      0.115352,
      "i"
    ],
    [
      0.746809,
      "n"
    ],
    [
      0.215619,
      "s"
    ],
    [
      0.201561,
      "t"
    ],
    [
      0.134818,
      "a"
    ],
    [
      0.14362,
      "l"
    ],
    [
      0.157746,
      "l"
    ],
    [
      0.174461,
      " "
    ],
    [
      1.35578,
      "t"
    ],
    [
      0.103627,
      "h"
    ],
    [
      0.149235,
      "e"
    ],
    [
      0.529219,
      "_"
    ],
    [
      0.529011,
      "b"
    ],
    [
      0.291864,
      "r"
    ],
    [
      0.622684,
      "a"
    ],
    [
      0.128271,
      "i"
    ],
    [
      0.219996,
      "n"
    ],
    [
      0.51001,
      "_"
    ],
    [
      0.308096,
      "g"
    ],
    [
      0.194699,
      "a"
    ],
    [
      0.176266,
      "m"
    ],
    [
      0.577223,
      "e"
    ],
    [
      0.2106,
      "s"
    ],
    [
      0.685386,
      " "
    ],
    [
      0.205622,
      "-"
    ],
    [
      0.664294,
      "g"
    ],
    [
      2.573468,
      "\r\n"
    ],
    [
      0.794782,
      "\u001b[?25l"
    ],
    [
      0.001191,
      "\u001b[0G"
    ],
    [
      0.000304,
      "▄ ╢░░░░░░░░░░░░░░░░░░░░░░░░░░░░░░░░░░░░░░░░░░░░░░░░░░░░░░░░░░░░░░░░░░░░░░░░░░░╟"
    ],
    [
      5.3e-05,
      "\r\n"
    ],
    [
      0.00022,
      "\u001b[?25h"
    ],
    [
      0.072313,
      "\u001b[1A"
    ],
    [
      0.000204,
      "\u001b[?25l"
    ],
    [
      9.7e-05,
      "\u001b[0G"
    ],
    [
      8.6e-05,
      "▀ ╢░░░░░░░░░░░░░░░░░░░░░░░░░░░░░░░░░░░░░░░░░░░░░░░░░░░░░░░░░░░░░░░░░░░░░░░░░░░╟"
    ],
    [
      4e-05,
      "\r\n"
    ],
    [
      0.000701,
      "\u001b[?25h"
    ],
    [
      0.070658,
      "\u001b[1A"
    ],
    [
      0.002885,
      "\u001b[?25l"
    ],
    [
      0.000102,
      "\u001b[0G"
    ],
    [
      7.8e-05,
      "▐ ╢░░░░░░░░░░░░░░░░░░░░░░░░░░░░░░░░░░░░░░░░░░░░░░░░░░░░░░░░░░░░░░░░░░░░░░░░░░░╟"
    ],
    [
      5.7e-05,
      "\r\n"
    ],
    [
      8.1e-05,
      "\u001b[?25h"
    ],
    [
      0.124012,
      "\u001b[1A\u001b[?25l\u001b[0G▄ ╢░░░░░░░░░░░░░░░░░░░░░░░░░░░░░░░░░░░░░░░░░░░░░░░░░░░░░░░░░░░░░░░░░░░░░░░░░░░╟\r\n\u001b[?25h"
    ],
    [
      0.25194,
      "\u001b[1A"
    ],
    [
      0.000121,
      "\u001b[?25l"
    ],
    [
      0.000112,
      "\u001b[0G"
    ],
    [
      7e-05,
      "▌ ╢░░░░░░░░░░░░░░░░░░░░░░░░░░░░░░░░░░░░░░░░░░░░░░░░░░░░░░░░░░░░░░░░░░░░░░░░░░░╟"
    ],
    [
      4.1e-05,
      "\r\n"
    ],
    [
      7.4e-05,
      "\u001b[?25h"
    ],
    [
      0.246291,
      "\u001b[1A"
    ],
    [
      0.000124,
      "\u001b[?25l"
    ],
    [
      6.7e-05,
      "\u001b[0G"
    ],
    [
      7.1e-05,
      "▀ ╢░░░░░░░░░░░░░░░░░░░░░░░░░░░░░░░░░░░░░░░░░░░░░░░░░░░░░░░░░░░░░░░░░░░░░░░░░░░╟"
    ],
    [
      3.4e-05,
      "\r\n"
    ],
    [
      7.4e-05,
      "\u001b[?25h"
    ],
    [
      0.063355,
      "\u001b[1A"
    ],
    [
      0.000112,
      "\u001b[?25l"
    ],
    [
      6.6e-05,
      "\u001b[0G"
    ],
    [
      0.000108,
      "▐ ╢░░░░░░░░░░░░░░░░░░░░░░░░░░░░░░░░░░░░░░░░░░░░░░░░░░░░░░░░░░░░░░░░░░░░░░░░░░░╟"
    ],
    [
      3.6e-05,
      "\r\n"
    ],
    [
      7.2e-05,
      "\u001b[?25h"
    ],
    [
      0.054039,
      "\u001b[1A"
    ],
    [
      0.000137,
      "\u001b[?25l"
    ],
    [
      6.8e-05,
      "\u001b[0G"
    ],
    [
      9.8e-05,
      "loadRequestedDeps → addNa ▐ ╢██████████░░░░░░░░░░░░░░░░░░░░░░░░░░░░░░░░░░░░░░░╟"
    ],
    [
      4e-05,
      "\r\n"
    ],
    [
      8.3e-05,
      "\u001b[?25h"
    ],
    [
      0.066633,
      "\u001b[1A"
    ],
    [
      0.000125,
      "\u001b[?25l"
    ],
    [
      6.9e-05,
      "\u001b[0G"
    ],
    [
      0.000115,
      "loadRequestedDeps → after ▀ ╢██████████░░░░░░░░░░░░░░░░░░░░░░░░░░░░░░░░░░░░░░░╟"
    ],
    [
      4e-05,
      "\r\n"
    ],
    [
      7.9e-05,
      "\u001b[?25h"
    ],
    [
      0.0497,
      "\u001b[1A\u001b[?25l\u001b[0GloadDep:readline-sync → r ▀ ╢██████████░░░░░░░░░░░░░░░░░░░░░░░░░░░░░░░░░░░░░░░╟\r\n\u001b[?25h"
    ],
    [
      0.217683,
      "\u001b[1A\u001b[?25l\u001b[0GloadDep:readline-sync → n ▐ ╢██████████░░░░░░░░░░░░░░░░░░░░░░░░░░░░░░░░░░░░░░░╟\r\n\u001b[?25h"
    ],
    [
      0.250484,
      "\u001b[1A\u001b[?25l\u001b[0GloadDep:readline-sync → n ▄ ╢██████████░░░░░░░░░░░░░░░░░░░░░░░░░░░░░░░░░░░░░░░╟\r\n\u001b[?25h"
    ],
    [
      0.058744,
      "\u001b[1A"
    ],
    [
      0.000558,
      "\u001b[?25l"
    ],
    [
      0.000455,
      "\u001b[0G"
    ],
    [
      0.000262,
      "loadDep:readline-sync → 3 ▌ ╢██████████░░░░░░░░░░░░░░░░░░░░░░░░░░░░░░░░░░░░░░░╟"
    ],
    [
      0.000249,
      "\r\n"
    ],
    [
      0.000139,
      "\u001b[?25h"
    ],
    [
      0.04823,
      "\u001b[1A"
    ],
    [
      0.005091,
      "\u001b[?25l"
    ],
    [
      0.000104,
      "\u001b[0G"
    ],
    [
      8.1e-05,
      "loadDep:readline-sync → g ▀ ╢██████████░░░░░░░░░░░░░░░░░░░░░░░░░░░░░░░░░░░░░░░╟"
    ],
    [
      4.2e-05,
      "\r\n"
    ],
    [
      7.9e-05,
      "\u001b[?25h"
    ],
    [
      0.044867,
      "\u001b[1A"
    ],
    [
      0.003149,
      "\u001b[?25l"
    ],
    [
      0.000132,
      "\u001b[0G"
    ],
    [
      8.4e-05,
      "loadDep:readline-sync → a ▌ ╢██████████░░░░░░░░░░░░░░░░░░░░░░░░░░░░░░░░░░░░░░░╟"
    ],
    [
      3.6e-05,
      "\r\n"
    ],
    [
      6.8e-05,
      "\u001b[?25h"
    ],
    [
      0.046551,
      "\u001b[1A"
    ],
    [
      0.00211,
      "\u001b[?25l"
    ],
    [
      0.001547,
      "\u001b[0G"
    ],
    [
      0.000165,
      "diffTrees                 ▄ ╢█████████████████████████████░░░░░░░░░░░░░░░░░░░░╟"
    ],
    [
      3.8e-05,
      "\r\n"
    ],
    [
      8.8e-05,
      "\u001b[?25h"
    ],
    [
      0.051017,
      "\u001b[1A"
    ],
    [
      0.000113,
      "\u001b[?25l"
    ],
    [
      6.5e-05,
      "\u001b[0G"
    ],
    [
      0.000118,
      "extract → unbuild         ▀ ╢██████████████████████████████████░░░░░░░░░░░░░░░╟"
    ],
    [
      3.7e-05,
      "\r\n"
    ],
    [
      7.8e-05,
      "\u001b[?25h"
    ],
    [
      0.054971,
      "\u001b[1A"
    ],
    [
      0.000127,
      "\u001b[?25l"
    ],
    [
      6.6e-05,
      "\u001b[0G"
    ],
    [
      6.8e-05,
      "extract → gunzTarPerm     ▐ ╢██████████████████████████████████░░░░░░░░░░░░░░░╟"
    ],
    [
      3.5e-05,
      "\r\n"
    ],
    [
      0.000102,
      "\u001b[?25h"
    ],
    [
      0.049417,
      "\u001b[1A"
    ],
    [
      0.000167,
      "\u001b[?25l"
    ],
    [
      6.9e-05,
      "\u001b[0G"
    ],
    [
      7.3e-05,
      "extract → gunzTarPerm     ▌ ╢██████████████████████████████████░░░░░░░░░░░░░░░╟"
    ],
    [
      3.6e-05,
      "\r\n"
    ],
    [
      6.6e-05,
      "\u001b[?25h"
    ],
    [
      0.049309,
      "\u001b[1A"
    ],
    [
      0.001509,
      "\u001b[?25l"
    ],
    [
      8.4e-05,
      "\u001b[0G"
    ],
    [
      7.1e-05,
      "extract → gunzTarPerm     ▐ ╢██████████████████████████████████░░░░░░░░░░░░░░░╟"
    ],
    [
      3.6e-05,
      "\r\n"
    ],
    [
      7.6e-05,
      "\u001b[?25h"
    ],
    [
      0.048772,
      "\u001b[1A"
    ],
    [
      0.000498,
      "\u001b[?25l"
    ],
    [
      8e-05,
      "\u001b[0G"
    ],
    [
      6.6e-05,
      "extract:the_brain_games   ▌ ╢█████████████████████████████████████░░░░░░░░░░░░╟"
    ],
    [
      3.4e-05,
      "\r\n"
    ],
    [
      7.6e-05,
      "\u001b[?25h"
    ],
    [
      0.056631,
      "\u001b[1A\u001b[?25l\u001b[0Gbuild                     ▄ ╢██████████████████████████████████████████░░░░░░░╟\r\n\u001b[?25h"
    ],
    [
      0.051044,
      "\u001b[1A\u001b[?25l\u001b[0Gbuild:readline-sync → lin ▐ ╢██████████████████████████████████████████░░░░░░░╟\r\n\u001b[?25h"
    ],
    [
      0.013468,
      "\u001b[?25h"
    ],
    [
      0.007911,
      "\u001b[1A\u001b[0G\u001b[K/usr/local/bin/brain-games -> /usr/local/lib/node_modules/the_brain_games/dist/bin/brain-games.js\r\n\u001b[?25l\u001b[0Gbuild:readline-sync       ▀ ╢██████████████████████████████████████████░░░░░░░╟\r\n\u001b[?25h\u001b[?25h\u001b[1A\u001b[0G\u001b[K/usr/local/bin/brain-even -> /usr/local/lib/node_modules/the_brain_games/dist/bin/brain-even.js\r\n\u001b[?25l\u001b[0G"
    ],
    [
      0.009109,
      "build:readline-sync       ▀ ╢██████████████████████████████████████████░░░░░░░╟\r\n\u001b[?25h"
    ],
    [
      0.05016,
      "\u001b[1A\u001b[?25l\u001b[0GrollbackFailedOptional    ▀ ╢████████████████████████████████████████████░░░░░╟\r\n\u001b[?25h\u001b[?25h\u001b[1A\u001b[0G\u001b[K\u001b[?25l\u001b[0GrunTopLevelLifecycles     ▀ ╢███████████████████████████████████████████████░░╟\r\n\u001b[?25h\u001b[?25h\u001b[1A"
    ],
    [
      0.011458,
      "\u001b[0G\u001b[K"
    ],
    [
      0.007573,
      "/usr/local/lib"
    ],
    [
      0.001742,
      "\r\n"
    ],
    [
      5.5e-05,
      "└─┬ \u001b[40m\u001b[33mthe_brain_games@1.2.3\u001b[0m\u001b[0m "
    ],
    [
      3.5e-05,
      "\r\n"
    ],
    [
      3.3e-05,
      "  └── \u001b[40m\u001b[33mreadline-sync@1.4.7\u001b[0m\u001b[0m "
    ],
    [
      3.1e-05,
      "\r\n"
    ],
    [
      3.1e-05,
      "\r\n"
    ],
    [
      0.000283,
      "\u001b[?25l"
    ],
    [
      0.018096,
      "\u001b[0GrunTopLevelLifecycles     ▀ ╢███████████████████████████████████████████████░░╟\r\n\u001b[?25h\u001b[?25h\u001b[1A\u001b[0G\u001b[K\u001b[?25h\u001b[0G\u001b[K"
    ],
    [
      0.010179,
      "\u001b]0;root@vubuntu4dev: /home/vladves/vcs/repo_01\u0007root@vubuntu4dev:/home/vladves/vcs/repo_01# "
    ],
    [
      5.403192,
      "b"
    ],
    [
      0.524081,
      "r"
    ],
    [
      0.220884,
      "i"
    ],
    [
      0.275083,
      "n"
    ],
    [
      0.778172,
      "\b\u001b[K"
    ],
    [
      0.143712,
      "\b\u001b[K"
    ],
    [
      0.118002,
      "a"
    ],
    [
      0.487114,
      "i"
    ],
    [
      0.19096,
      "n"
    ],
    [
      0.8625,
      "0"
    ],
    [
      1.047691,
      "\b\u001b[K"
    ],
    [
      0.283573,
      "-"
    ],
    [
      0.477145,
      "e"
    ],
    [
      0.291988,
      "v"
    ],
    [
      0.22075,
      "e"
    ],
    [
      0.796487,
      "n"
    ],
    [
      3.620644,
      "\r\n"
    ],
    [
      0.130755,
      "Welcome to the Brain Games!"
    ],
    [
      7.7e-05,
      "\r\n"
    ],
    [
      0.000839,
      "Answer \"yes\" if number even otherwise anser \"no\""
    ],
    [
      5e-05,
      "\r\n"
    ],
    [
      0.004772,
      "May I have your name? "
    ],
    [
      2.801773,
      "J"
    ],
    [
      0.226782,
      "o"
    ],
    [
      0.219955,
      "n"
    ],
    [
      0.30901,
      "h"
    ],
    [
      1.026806,
      "\r\nHellow Jonh!\r\nQuestion: 9\r\nYour answer: "
    ],
    [
      1.870218,
      "n"
    ],
    [
      0.149967,
      "o"
    ],
    [
      0.514417,
      "\r\nCorrect!\r\nQuestion: 2\r\nYour answer: "
    ],
    [
      1.763554,
      "e"
    ],
    [
      0.71102,
      "\b \b"
    ],
    [
      0.655147,
      "y"
    ],
    [
      0.2215,
      "e"
    ],
    [
      0.19915,
      "s"
    ],
    [
      0.540674,
      "\r\nCorrect!\r\nQuestion: 5\r\nYour answer: "
    ],
    [
      1.057549,
      "n"
    ],
    [
      0.150924,
      "o"
    ],
    [
      0.458306,
      "\r\nCorrect!\r\nCongratulations, Jonh\r\n"
    ],
    [
      0.001378,
      "\u001b]0;root@vubuntu4dev: /home/vladves/vcs/repo_01\u0007root@vubuntu4dev:/home/vladves/vcs/repo_01# "
    ],
    [
      1.761355,
      "brain-even"
    ],
    [
      1.420515,
      "\r\n"
    ],
    [
      0.144076,
      "Welcome to the Brain Games!"
    ],
    [
      7.7e-05,
      "\r\n"
    ],
    [
      0.000873,
      "Answer \"yes\" if number even otherwise anser \"no\""
    ],
    [
      5e-05,
      "\r\n"
    ],
    [
      0.004841,
      "May I have your name? "
    ],
    [
      5.338392,
      "n"
    ],
    [
      0.079304,
      "j"
    ],
    [
      0.308552,
      "a"
    ],
    [
      0.2191,
      "f"
    ],
    [
      0.003458,
      "d"
    ],
    [
      0.738026,
      "\r\nHellow njafd!\r\nQuestion: 9\r\nYour answer: "
    ],
    [
      1.800439,
      "e"
    ],
    [
      0.73235,
      "\b \b"
    ],
    [
      0.422826,
      "y"
    ],
    [
      0.141645,
      "e"
    ],
    [
      0.478257,
      "s"
    ],
    [
      0.75952,
      "\r\n'yes' is wrong answer ;(. Correc answer was 'no'\r\n\r\n        Let's try again, njafd!\r\n"
    ],
    [
      0.001465,
      "\u001b]0;root@vubuntu4dev: /home/vladves/vcs/repo_01\u0007root@vubuntu4dev:/home/vladves/vcs/repo_01# "
    ],
    [
      2.256281,
      "brain-even"
    ],
    [
      0.901759,
      "\r\n"
    ],
    [
      0.151198,
      "Welcome to the Brain Games!"
    ],
    [
      0.002021,
      "\r\n"
    ],
    [
      0.001238,
      "Answer \"yes\" if number even otherwise anser \"no\""
    ],
    [
      5.2e-05,
      "\r\n"
    ],
    [
      0.005234,
      "May I have your name? "
    ],
    [
      1.742198,
      "d"
    ],
    [
      0.189168,
      "d"
    ],
    [
      0.176457,
      "d"
    ],
    [
      0.431732,
      "\r\nHellow ddd!\r\nQuestion: 2\r\nYour answer: "
    ],
    [
      1.857631,
      "a"
    ],
    [
      0.241982,
      "d"
    ],
    [
      0.177573,
      "f"
    ],
    [
      0.277396,
      "2"
    ],
    [
      0.115882,
      "3"
    ],
    [
      0.499587,
      "\r\n'adf23' is wrong answer ;(. Correc answer was 'yes'\r\n\r\n        Let's try again, ddd!\r\n"
    ],
    [
      0.001376,
      "\u001b]0;root@vubuntu4dev: /home/vladves/vcs/repo_01\u0007root@vubuntu4dev:/home/vladves/vcs/repo_01# "
    ]
  ]
}